[
  {
    "variation": "default",
    "name": "Default",
    "slice_type": "quote",
    "items": [],
    "primary": {
      "quote": [
        {
          "type": "paragraph",
          "text": "Occaecat ipsum mollit est cillum dolore magna amet anim est occaecat nulla nisi. Ea adipisicing pariatur enim reprehenderit adipisicing labore velit occaecat labore cupidatat tempor ut culpa proident. Nostrud ea aliqua nisi commodo excepteur ad sint ipsum anim est.",
          "spans": []
        }
      ],
      "source": "benchmark e-business interfaces"
    }
  }
]